mac.v
module mac(in_a, in_b, in_valid_a, in_valid_b, clk, 
			reset, mac_out, out_valid);

//input output declartion			
input signed [3:0] 	 in_a, in_b;
input 			     in_valid_a, in_valid_b;
input			     clk, reset;
output reg signed [10:0] mac_out;
output 		reg          out_valid;


//////////////////////////////////////////////////////////////////////////
parameter  IDLE  = 2'b000 ;
parameter WAIT_A = 2'b001 ;
parameter WAIT_B = 2'b010 ;
parameter  MAC   = 2'b011 ;

reg out_sig ;
reg [3:0] counter ;
reg [1:0] state_Next , state ;
reg signed [3:0] reg_a , reg_b ;
reg signed [10:0] reg_c , temp_out;

always@(negedge clk)
begin
	if(reset)
		counter <= 4'd0 ;
	else if(counter==4'd8)
		if(in_valid_a&in_valid_b)
		counter <= 4'd1 ;
		else
		counter <= 4'd0 ;
	else if(state==MAC)
		counter <= counter + 4'd1 ;
end

always@(posedge clk )
begin
	if(reset)
		state <= IDLE ;
	else
		state <= state_Next ;
end

always@(*)
begin
	case(state)
		IDLE : if(in_valid_a&in_valid_b) 
				 state_Next = MAC   ;
			   else if(in_valid_a) 
				state_Next = WAIT_B ; 
			   else if(in_valid_b) 
			    state_Next = WAIT_A ; 
			   else	        state_Next = IDLE   ;
		
		WAIT_A : if(in_valid_a) 
				  state_Next = MAC ; 
				 else state_Next = WAIT_A ;
				 
		WAIT_B : if(in_valid_b) 
		          state_Next = MAC ; 
				 else state_Next = WAIT_B ;
		
		MAC    : if(in_valid_a&in_valid_b) 
				 state_Next = MAC ; 
				 else if(in_valid_a)
					state_Next = WAIT_B ;
				 else if(in_valid_b)
					state_Next = WAIT_A ;
				 else state_Next = IDLE ;
		default : state_Next = IDLE ;
	endcase
end

always@(posedge clk)
begin
	if(in_valid_a)
		reg_a <= in_a ;
end

always@(posedge clk)
begin
	if(in_valid_b)
		reg_b <= in_b ;
end

always@(negedge clk)
begin
	if(reset)
		reg_c <= 11'd0 ;
	else if(counter==4'd8)
		if(in_valid_a&in_valid_b)
		reg_c <= reg_a*reg_b ;
		else
		reg_c <= 11'd0 ;
	else if(state==MAC)
		reg_c <= reg_c + (reg_a*reg_b) ;
	
end

always@(posedge clk)
begin
	if(counter>=4'd1&&counter<=4'd8)
		temp_out <= reg_c ;
end

always@(posedge clk)
begin
	if(counter==4'd8)
		out_sig <= 1 ;
	else
		out_sig <= 0 ;
end

always@(posedge clk)
begin
	if(out_sig)
		out_valid <= 1 ;
	else
		out_valid <= 0 ;
end

always@(posedge clk)
begin
	if(out_sig)
		mac_out <= temp_out ;
	
end

endmodule

mac_tb.v

`define DATA_NUM 249
`define CYCLE 10
`define PATTERN "pattern_in.txt"
`define EXPECT "out_answer.txt"
`timescale 1ns/10ps

module mac_tb ;

reg [3:0] in_a ,in_b ; 
reg in_valid_a,in_valid_b;
reg clk,reset ;
reg [3:0]count;
wire [10:0] mac_out ;

wire out_valid ;

reg [9:0]pattern_in[0:`DATA_NUM-1] ;

reg [10:0]ans[0:9] ;

/* 
reg out_valid_exp ;

reg [10:0] mac_out_exp ; */

mac u_mac (	.mac_out(mac_out),
			.out_valid(out_valid),
			.in_a(in_a),
			.in_b(in_b),
			.in_valid_a(in_valid_a),
			.in_valid_b(in_valid_b),
			.clk(clk),
			.reset(reset)
) ;

always begin #(`CYCLE/2) clk=~clk ; end  //clock generation

initial begin
$readmemb(`PATTERN,pattern_in) ;
$readmemb(`EXPECT,ans) ;
end


integer i ,err ,check;

initial begin
clk=1'b0 ;
err=0 ;
check=0;
count=0;
@(negedge clk) reset=1'b1 ;
#(`CYCLE*2) reset=1'b0 ;

@(negedge clk) ;

  for(i=0;i<`DATA_NUM;i=i+1) begin
    {in_a,in_b,in_valid_a,in_valid_b}=pattern_in[i] ;
//    {mac_out_exp,out_valid_exp}=ans[i] ;
    @(negedge clk) ;
//@(posedge clk) ;
    if(out_valid) 
	begin
	
		if(mac_out==ans[count])

			check=check+1;

		else begin
			err=err+1;
			$display($time,"Error at in_a=%b, in_b=%b, in_valid_a=%b, in_valid_b=%b",in_a,in_b,in_valid_a,in_valid_b) ;
			$display($time,"Expect   : mac_out=%b",ans[count]) ;
    		$display($time,"Your ans : mac_out=%b\n\n",mac_out) ;	
		end
		count = count+1;
    end
  end
end


initial
begin
   $dumpfile("mac.vcd");
   $dumpvars;
end


initial begin

#(`CYCLE*255) ;
if(err==0&&check==10) 
begin
$display("-------------------   mac check successfully   -------------------");
$display("            $$              ");
$display("           $  $");
$display("           $  $");
$display("          $   $");
$display("         $    $");
$display("$$$$$$$$$     $$$$$$$$");
$display("$$$$$$$              $");
$display("$$$$$$$              $");
$display("$$$$$$$              $");
$display("$$$$$$$              $");
$display("$$$$$$$              $");
$display("$$$$$$$$$$$$         $$");
$display("$$$$$      $$$$$$$$$$");
end
else if((err==0)&&(check!=10)) begin
$display("-----------   Oops! Something wrong with your code!   ------------");
end
else $display("-------------------   There are %d errors   -------------------", err);

$finish ;

end

endmodule

mac.vcd
$date
	Sun Feb 17 22:15:20 2019
$end
$version
	ModelSim Version 10.4a
$end
$timescale
	10ps
$end

$scope module mac_tb $end
$var reg 4 ! in_a [3:0] $end
$var reg 4 " in_b [3:0] $end
$var reg 1 # in_valid_a $end
$var reg 1 $ in_valid_b $end
$var reg 1 % clk $end
$var reg 1 & reset $end
$var reg 4 ' count [3:0] $end
$var wire 1 ( mac_out [10] $end
$var wire 1 ) mac_out [9] $end
$var wire 1 * mac_out [8] $end
$var wire 1 + mac_out [7] $end
$var wire 1 , mac_out [6] $end
$var wire 1 - mac_out [5] $end
$var wire 1 . mac_out [4] $end
$var wire 1 / mac_out [3] $end
$var wire 1 0 mac_out [2] $end
$var wire 1 1 mac_out [1] $end
$var wire 1 2 mac_out [0] $end
$var wire 1 3 out_valid $end
$var integer 32 4 i $end
$var integer 32 5 err $end
$var integer 32 6 check $end

$scope module u_mac $end
$var parameter 2 7 IDLE $end
$var parameter 2 8 WAIT_A $end
$var parameter 2 9 WAIT_B $end
$var parameter 2 : MAC $end
$var wire 1 ; in_a [3] $end
$var wire 1 < in_a [2] $end
$var wire 1 = in_a [1] $end
$var wire 1 > in_a [0] $end
$var wire 1 ? in_b [3] $end
$var wire 1 @ in_b [2] $end
$var wire 1 A in_b [1] $end
$var wire 1 B in_b [0] $end
$var wire 1 C in_valid_a $end
$var wire 1 D in_valid_b $end
$var wire 1 E clk $end
$var wire 1 F reset $end
$var reg 11 G mac_out [10:0] $end
$var reg 1 H out_valid $end
$var reg 1 I out_sig $end
$var reg 4 J counter [3:0] $end
$var reg 2 K state_Next [1:0] $end
$var reg 2 L state [1:0] $end
$var reg 4 M reg_a [3:0] $end
$var reg 4 N reg_b [3:0] $end
$var reg 11 O reg_c [10:0] $end
$var reg 11 P temp_out [10:0] $end
$upscope $end
$upscope $end
$enddefinitions $end
#0
$dumpvars
bx !
bx "
x#
x$
0%
x&
b0 '
bx G
xH
xI
bx J
bx K
bx L
bx M
bx N
bx O
bx P
b0 7
b1 8
b10 9
b11 :
bx 4
b0 5
b0 6
x2
x1
x0
x/
x.
x-
x,
x+
x*
x)
x(
x3
xF
0E
xD
xC
xB
xA
x@
x?
x>
x=
x<
x;
$end
#500
1%
1E
0I
0H
03
#1000
0%
0E
1&
1F
#1500
1%
1E
b0 L
b0 K
#2000
0%
0E
b0 J
b0 O
#2500
1%
1E
#3000
0&
0%
0F
0E
b0 4
0$
0#
b1 "
b110 !
0>
1=
1<
0;
1B
0A
0@
0?
0D
0C
#3500
1%
1E
#4000
0%
0E
b1 4
1$
b1001 !
1>
0=
0<
1;
1D
b1 K
#4500
1%
1E
b1 L
b1 N
#5000
0%
0E
b10 4
0$
b10 "
b1110 !
0>
1=
1<
0B
1A
0D
#5500
1%
1E
#6000
0%
0E
b11 4
b100 "
b10 !
0<
0;
0A
1@
#6500
1%
1E
#7000
0%
0E
b100 4
1#
b110 "
b1010 !
1;
1A
1C
b11 K
#7500
1%
1E
b11 L
b1010 M
b10 K
#8000
0%
0E
b101 4
1$
0#
b0 "
b100 !
0=
1<
0;
0A
0@
1D
0C
b1 K
b1 J
b11111111010 O
#8500
1%
1E
b1 L
b0 N
b11111111010 P
#9000
0%
0E
b110 4
0$
1#
b111 "
b1001 !
1>
0<
1;
1B
1A
1@
0D
1C
b11 K
#9500
1%
1E
b11 L
b1001 M
b10 K
#10000
0%
0E
b111 4
0#
b10 "
b1100 !
0>
1<
0B
0@
0C
b0 K
b10 J
#10500
1%
1E
b0 L
#11000
0%
0E
b1000 4
b100 "
b10 !
1=
0<
0;
0A
1@
#11500
1%
1E
#12000
0%
0E
b1001 4
1$
1#
b11 "
b111 !
1>
1<
1B
1A
0@
1D
1C
b11 K
#12500
1%
1E
b11 L
b111 M
b11 N
#13000
0%
0E
b1010 4
b10 "
b10 !
0>
0<
0B
b11 J
b1111 O
#13500
1%
1E
b10 M
b10 N
b1111 P
#14000
0%
0E
b1011 4
0$
0#
b100 "
0A
1@
0D
0C
b0 K
b100 J
b10011 O
#14500
1%
1E
b0 L
b10011 P
#15000
0%
0E
b1100 4
b1 "
b11 !
1>
1B
0@
#15500
1%
1E
#16000
0%
0E
b1101 4
b100 "
b1 !
0=
0B
1@
#16500
1%
1E
#17000
0%
0E
b1110 4
b101 "
b1010 !
0>
1=
1;
1B
#17500
1%
1E
#18000
0%
0E
b1111 4
1#
b11 !
1>
0;
1C
b10 K
#18500
1%
1E
b10 L
b11 M
#19000
0%
0E
b10000 4
1$
0#
b0 "
0B
0@
1D
0C
b11 K
#19500
1%
1E
b11 L
b0 N
b1 K
#20000
0%
0E
b10001 4
0$
1#
b11 "
b100 !
0>
0=
1<
1B
1A
0D
1C
b10 K
b101 J
#20500
1%
1E
b10 L
b100 M
#21000
0%
0E
b10010 4
1$
0#
b100 "
b11 !
1>
1=
0<
0B
0A
1@
1D
0C
b11 K
#21500
1%
1E
b11 L
b100 N
b1 K
#22000
0%
0E
b10011 4
0$
1#
b1111 "
b1111 !
1<
1;
1B
1A
1?
0D
1C
b10 K
b110 J
b100011 O
#22500
1%
1E
b10 L
b1111 M
b100011 P
#23000
0%
0E
b10100 4
1$
0#
b0 "
0B
0A
0@
0?
1D
0C
b11 K
#23500
1%
1E
b11 L
b0 N
b1 K
#24000
0%
0E
b10101 4
0$
b11 "
b11 !
0<
0;
1B
1A
0D
b0 K
b111 J
#24500
1%
1E
b0 L
#25000
0%
0E
b10110 4
b100 "
b100 !
0>
0=
1<
0B
0A
1@
#25500
1%
1E
#26000
0%
0E
b10111 4
1$
b111 "
b111 !
1>
1=
1B
1A
1D
b1 K
#26500
1%
1E
b1 L
b111 N
#27000
0%
0E
b11000 4
0$
1#
b1 "
b1110 !
0>
1;
0A
0@
0D
1C
b11 K
#27500
1%
1E
b11 L
b1110 M
b10 K
#28000
0%
0E
b11001 4
1$
b1111 "
b0 !
0=
0<
0;
1A
1@
1?
1D
b11 K
b1000 J
b10101 O
#28500
1%
1E
b0 M
b1111 N
b10101 P
1I
#29000
0%
0E
b11010 4
0$
0#
b110 "
b10 !
1=
0B
0?
0D
0C
b0 K
b1 J
b0 O
#29500
1%
1E
b0 L
b0 P
0I
1H
b10101 G
13
12
01
10
0/
1.
0-
0,
0+
0*
0)
0(
#30000
0%
0E
b1 6
b1 '
b11011 4
1$
b1111 "
b101 !
1>
0=
1<
1B
1?
1D
b1 K
#30500
1%
1E
b1 L
0H
03
#31000
0%
0E
b11100 4
0$
1#
b111 "
b1000 !
0>
0<
1;
0?
0D
1C
b11 K
#31500
1%
1E
b11 L
b1000 M
b10 K
#32000
0%
0E
b11101 4
0#
b11 "
b1001 !
1>
0@
0C
b0 K
b10 J
b1000 O
#32500
1%
1E
b0 L
b1000 P
#33000
0%
0E
b11110 4
b0 "
b11 !
1=
0;
0B
0A
#33500
1%
1E
#34000
0%
0E
b11111 4
1#
b11 "
b100 !
0>
0=
1<
1B
1A
1C
b10 K
#34500
1%
1E
b10 L
b100 M
#35000
0%
0E
b100000 4
0#
b1111 "
b1011 !
1>
1=
0<
1;
1@
1?
0C
#35500
1%
1E
#36000
0%
0E
b100001 4
b1110 !
0>
1<
#36500
1%
1E
#37000
0%
0E
b100010 4
1$
b1 "
0A
0@
0?
1D
b11 K
#37500
1%
1E
b11 L
b1 N
b1 K
#38000
0%
0E
b100011 4
0$
b10 "
b1010 !
0<
0B
1A
0D
b0 K
b11 J
b1100 O
#38500
1%
1E
b0 L
b1100 P
#39000
0%
0E
b100100 4
1#
b0 "
b1110 !
1<
0A
1C
b10 K
#39500
1%
1E
b10 L
b1110 M
#40000
0%
0E
b100101 4
1$
0#
b11 "
b1 !
1>
0=
0<
0;
1B
1A
1D
0C
b11 K
#40500
1%
1E
b11 L
b11 N
b1 K
#41000
0%
0E
b100110 4
0$
b111 !
1=
1<
0D
b0 K
b100 J
b110 O
#41500
1%
1E
b0 L
b110 P
#42000
0%
0E
b100111 4
b0 "
b10 !
0>
0<
0B
0A
#42500
1%
1E
#43000
0%
0E
b101000 4
1$
b110 "
b1010 !
1;
1A
1@
1D
b1 K
#43500
1%
1E
b1 L
b110 N
#44000
0%
0E
b101001 4
0$
1#
b101 "
b1011 !
1>
1B
0A
0D
1C
b11 K
#44500
1%
1E
b11 L
b1011 M
b10 K
#45000
0%
0E
b101010 4
0#
b0 "
b10 !
0>
0;
0B
0@
0C
b0 K
b101 J
b11111101000 O
#45500
1%
1E
b0 L
b11111101000 P
#46000
0%
0E
b101011 4
b10 "
b110 !
1<
1A
#46500
1%
1E
#47000
0%
0E
b101100 4
1$
1#
b101 "
b101 !
1>
0=
1B
0A
1@
1D
1C
b11 K
#47500
1%
1E
b11 L
b101 M
b101 N
#48000
0%
0E
b101101 4
0#
b11 "
b110 !
0>
1=
1A
0@
0C
b1 K
b110 J
b1 O
#48500
1%
1E
b1 L
b11 N
b1 P
#49000
0%
0E
b101110 4
0$
1#
b100 "
b10 !
0<
0B
0A
1@
0D
1C
b11 K
#49500
1%
1E
b11 L
b10 M
b10 K
#50000
0%
0E
b101111 4
1$
0#
b110 "
b1010 !
1;
1A
1D
0C
b1 K
b111 J
b111 O
#50500
1%
1E
b1 L
b110 N
b111 P
#51000
0%
0E
b110000 4
0$
1#
b111 "
b0 !
0=
0;
1B
0D
1C
b11 K
#51500
1%
1E
b11 L
b0 M
b10 K
#52000
0%
0E
b110001 4
1$
b110 "
b101 !
1>
1<
0B
1D
b11 K
b1000 J
#52500
1%
1E
b101 M
1I
#53000
0%
0E
b110010 4
0$
0#
b0 "
b111 !
1=
0A
0@
0D
0C
b0 K
b1 J
b11110 O
#53500
1%
1E
b0 L
b11110 P
0I
1H
b111 G
13
11
0.
#54000
0%
0E
b10 6
b10 '
b110011 4
b110 "
b1000 !
0>
0=
0<
1;
1A
1@
#54500
1%
1E
0H
03
#55000
0%
0E
b110100 4
b11 "
b100 !
1<
0;
1B
0@
#55500
1%
1E
#56000
0%
0E
b110101 4
b0 "
b10 !
1=
0<
0B
0A
#56500
1%
1E
#57000
0%
0E
b110110 4
b1111 "
b1110 !
1<
1;
1B
1A
1@
1?
#57500
1%
1E
#58000
0%
0E
b110111 4
b10 "
b1000 !
0=
0<
0B
0@
0?
#58500
1%
1E
#59000
0%
0E
b111000 4
b111 "
b1110 !
1=
1<
1B
1@
#59500
1%
1E
#60000
0%
0E
b111001 4
b101 "
b1101 !
1>
0=
0A
#60500
1%
1E
#61000
0%
0E
b111010 4
b1 "
b111 !
1=
0;
0@
#61500
1%
1E
#62000
0%
0E
b111011 4
1$
b1111 "
b1100 !
0>
0=
1;
1A
1@
1?
1D
b1 K
#62500
1%
1E
b1 L
b1111 N
#63000
0%
0E
b111100 4
0$
1#
b10 "
b1101 !
1>
0B
0@
0?
0D
1C
b11 K
#63500
1%
1E
b11 L
b1101 M
b10 K
#64000
0%
0E
b111101 4
0#
b100 "
b0 !
0>
0<
0;
0A
1@
0C
b0 K
b10 J
b100001 O
#64500
1%
1E
b0 L
b100001 P
#65000
0%
0E
b111110 4
b101 "
b1101 !
1>
1<
1;
1B
#65500
1%
1E
#66000
0%
0E
b111111 4
1$
1#
b11 "
b11 !
1=
0<
0;
1A
0@
1D
1C
b11 K
#66500
1%
1E
b11 L
b11 M
b11 N
#67000
0%
0E
b1000000 4
0#
b100 "
b1100 !
0>
0=
1<
1;
0B
0A
1@
0C
b1 K
b11 J
b101010 O
#67500
1%
1E
b1 L
b100 N
b101010 P
#68000
0%
0E
b1000001 4
0$
1#
b1111 "
b1001 !
1>
0<
1B
1A
1?
0D
1C
b11 K
#68500
1%
1E
b11 L
b1001 M
b10 K
#69000
0%
0E
b1000010 4
0#
b0 "
b101 !
1<
0;
0B
0A
0@
0?
0C
b0 K
b100 J
b1110 O
#69500
1%
1E
b0 L
b1110 P
#70000
0%
0E
b1000011 4
b11 "
b11 !
1=
0<
1B
1A
#70500
1%
1E
#71000
0%
0E
b1000100 4
b101 "
b1100 !
0>
0=
1<
1;
0A
1@
#71500
1%
1E
#72000
0%
0E
b1000101 4
b1111 "
b110 !
1=
0;
1A
1?
#72500
1%
1E
#73000
0%
0E
b1000110 4
b111 "
b1 !
1>
0=
0<
0?
#73500
1%
1E
#74000
0%
0E
b1000111 4
1$
1#
b100 "
b10 !
0>
1=
0B
0A
1D
1C
b11 K
#74500
1%
1E
b11 L
b10 M
#75000
0%
0E
b1001000 4
b101 !
1>
0=
1<
b101 J
b10110 O
#75500
1%
1E
b101 M
b10110 P
#76000
0%
0E
b1001001 4
0$
0#
b111 "
b1001 !
0<
1;
1B
1A
0D
0C
b0 K
b110 J
b101010 O
#76500
1%
1E
b0 L
b101010 P
#77000
0%
0E
b1001010 4
1#
b11 "
b1010 !
0>
1=
0@
1C
b10 K
#77500
1%
1E
b10 L
b1010 M
#78000
0%
0E
b1001011 4
0#
b110 "
b1001 !
1>
0=
0B
1@
0C
#78500
1%
1E
#79000
0%
0E
b1001100 4
b100 "
b11 !
1=
0;
0A
#79500
1%
1E
#80000
0%
0E
b1001101 4
1$
b11 "
b101 !
0=
1<
1B
1A
0@
1D
b11 K
#80500
1%
1E
b11 L
b11 N
b1 K
#81000
0%
0E
b1001110 4
0$
b101 "
b1100 !
0>
1;
0A
1@
0D
b0 K
b111 J
b11000 O
#81500
1%
1E
b0 L
b11000 P
#82000
0%
0E
b1001111 4
1$
1#
b100 "
0B
1D
1C
b11 K
#82500
1%
1E
b11 L
b1100 M
b100 N
#83000
0%
0E
b1010000 4
0$
b10 "
b1011 !
1>
1=
0<
1A
0@
0D
b10 K
b1000 J
b1000 O
#83500
1%
1E
b10 L
b1011 M
b1000 P
1I
#84000
0%
0E
b1010001 4
0#
b1 "
b1111 !
1<
1B
0A
0C
b0 J
b0 O
#84500
1%
1E
0I
1H
b1000 G
13
02
01
00
1/
#85000
0%
0E
b11 6
b11 '
b1010010 4
b111 "
b1110 !
0>
1A
1@
#85500
1%
1E
0H
03
#86000
0%
0E
b1010011 4
b0 "
b1011 !
1>
0<
0B
0A
0@
#86500
1%
1E
#87000
0%
0E
b1010100 4
1$
b100 "
b11 !
0;
1@
1D
b11 K
#87500
1%
1E
b11 L
b1 K
#88000
0%
0E
b1010101 4
b11 "
b100 !
0>
0=
1<
1B
1A
0@
b1 J
b11111101100 O
#88500
1%
1E
b1 L
b11 N
b11111101100 P
#89000
0%
0E
b1010110 4
0$
1#
b101 "
b0 !
0<
0A
1@
0D
1C
b11 K
#89500
1%
1E
b11 L
b0 M
b10 K
#90000
0%
0E
b1010111 4
1$
b111 "
b1000 !
1;
1A
1D
b11 K
b10 J
#90500
1%
1E
b1000 M
b111 N
#91000
0%
0E
b1011000 4
0$
0#
b1011 !
1>
1=
0D
0C
b0 K
b11 J
b11110110100 O
#91500
1%
1E
b0 L
b11110110100 P
#92000
0%
0E
b1011001 4
b1 "
b100 !
0>
0=
1<
0;
0A
0@
#92500
1%
1E
#93000
0%
0E
b1011010 4
1$
1D
b1 K
#93500
1%
1E
b1 L
b1 N
#94000
0%
0E
b1011011 4
0$
b110 !
1=
0D
#94500
1%
1E
#95000
0%
0E
b1011100 4
b11 "
b1100 !
0=
1;
1A
#95500
1%
1E
#96000
0%
0E
b1011101 4
b1 "
b1000 !
0<
0A
#96500
1%
1E
#97000
0%
0E
b1011110 4
b110 "
b1110 !
1=
1<
0B
1A
1@
#97500
1%
1E
#98000
0%
0E
b1011111 4
1#
b100 "
b10 !
0<
0;
0A
1C
b11 K
#98500
1%
1E
b11 L
b10 M
b10 K
#99000
0%
0E
b1100000 4
1$
0#
b1 "
b1011 !
1>
1;
1B
0@
1D
0C
b1 K
b100 J
b11110110110 O
#99500
1%
1E
b1 L
b11110110110 P
#100000
0%
0E
b1100001 4
0$
1#
b10 "
b111 !
1<
0;
0B
1A
0D
1C
b11 K
#100500
1%
1E
b11 L
b111 M
b10 K
#101000
0%
0E
b1100010 4
1$
0#
b1110 !
0>
1;
1D
0C
b1 K
b101 J
b11110111101 O
#101500
1%
1E
b1 L
b10 N
b11110111101 P
#102000
0%
0E
b1100011 4
0$
1#
b111 "
b1 !
1>
0=
0<
0;
1B
1@
0D
1C
b11 K
#102500
1%
1E
b11 L
b1 M
b10 K
#103000
0%
0E
b1100100 4
1$
0#
b10 "
b1111 !
1=
1<
1;
0B
0@
1D
0C
b1 K
b110 J
b11110111111 O
#103500
1%
1E
b1 L
b11110111111 P
#104000
0%
0E
b1100101 4
0$
1#
b101 "
b101 !
0=
0;
1B
0A
1@
0D
1C
b11 K
#104500
1%
1E
b11 L
b101 M
b10 K
#105000
0%
0E
b1100110 4
0#
b111 "
1A
0C
b0 K
b111 J
b11111001001 O
#105500
1%
1E
b0 L
b11111001001 P
#106000
0%
0E
b1100111 4
b1 "
b1100 !
0>
1;
0A
0@
#106500
1%
1E
#107000
0%
0E
b1101000 4
b11 "
b1111 !
1>
1=
1A
#107500
1%
1E
#108000
0%
0E
b1101001 4
b1 "
b1101 !
0=
0A
#108500
1%
1E
#109000
0%
0E
b1101010 4
b1001 !
0<
#109500
1%
1E
#110000
0%
0E
b1101011 4
b100 "
b110 !
0>
1=
1<
0;
0B
1@
#110500
1%
1E
#111000
0%
0E
b1101100 4
1$
b0 !
0=
0<
1D
b1 K
#111500
1%
1E
b1 L
b100 N
#112000
0%
0E
b1101101 4
0$
b0 "
b111 !
1>
1=
1<
0@
0D
#112500
1%
1E
#113000
0%
0E
b1101110 4
b101 "
b11 !
0<
1B
1@
#113500
1%
1E
#114000
0%
0E
b1101111 4
1#
b11 "
b1001 !
0=
1;
1A
0@
1C
b11 K
#114500
1%
1E
b11 L
b1001 M
b10 K
#115000
0%
0E
b1110000 4
1$
b10 "
b100 !
0>
1<
0;
0B
1D
b11 K
b1000 J
b11110101101 O
#115500
1%
1E
b100 M
b10 N
b11110101101 P
1I
#116000
0%
0E
b1110001 4
b101 "
b110 !
1=
1B
0A
1@
b1 J
b1000 O
#116500
1%
1E
b110 M
b101 N
b1000 P
0I
1H
b11110101101 G
13
12
10
1-
1+
1*
1)
1(
#117000
0%
0E
b100 6
b100 '
b1110010 4
0$
0#
b0 "
b0 !
0=
0<
0B
0@
0D
0C
b0 K
b10 J
b100110 O
#117500
1%
1E
b0 L
b100110 P
0H
03
#118000
0%
0E
b1110011 4
1#
b110 "
b1010 !
1=
1;
1A
1@
1C
b10 K
#118500
1%
1E
b10 L
b1010 M
#119000
0%
0E
b1110100 4
1$
0#
b111 "
b101 !
1>
0=
1<
0;
1B
1D
0C
b11 K
#119500
1%
1E
b11 L
b111 N
b1 K
#120000
0%
0E
b1110101 4
1#
b0 "
b110 !
0>
1=
0B
0A
0@
1C
b11 K
b11 J
b11111111100 O
#120500
1%
1E
b110 M
b0 N
b11111111100 P
#121000
0%
0E
b1110110 4
b10 !
0<
b100 J
#121500
1%
1E
b10 M
#122000
0%
0E
b1110111 4
0#
b10 "
b1101 !
1>
0=
1<
1;
1A
0C
b1 K
b101 J
#122500
1%
1E
b1 L
b10 N
#123000
0%
0E
b1111000 4
0$
1#
b100 "
b1000 !
0>
0<
0A
1@
0D
1C
b11 K
#123500
1%
1E
b11 L
b1000 M
b10 K
#124000
0%
0E
b1111001 4
b10 "
b1111 !
1>
1=
1<
1A
0@
b110 J
b11111101100 O
#124500
1%
1E
b10 L
b1111 M
b11111101100 P
#125000
0%
0E
b1111010 4
0#
b11 "
1B
0C
#125500
1%
1E
#126000
0%
0E
b1111011 4
b1001 !
0=
0<
#126500
1%
1E
#127000
0%
0E
b1111100 4
1$
b10 "
b1100 !
0>
1<
0B
1D
b11 K
#127500
1%
1E
b11 L
b1 K
#128000
0%
0E
b1111101 4
0$
b0 "
b0 !
0<
0;
0A
0D
b0 K
b111 J
b11111101010 O
#128500
1%
1E
b0 L
b11111101010 P
#129000
0%
0E
b1111110 4
b10 "
b1011 !
1>
1=
1;
1A
#129500
1%
1E
#130000
0%
0E
b1111111 4
1#
b110 "
b1001 !
0=
1@
1C
b10 K
#130500
1%
1E
b10 L
b1001 M
#131000
0%
0E
b10000000 4
1$
0#
b1111 "
b111 !
1=
1<
0;
1B
1?
1D
0C
b11 K
#131500
1%
1E
b11 L
b1111 N
b1 K
#132000
0%
0E
b10000001 4
0$
b11 "
b11 !
0<
0@
0?
0D
b0 K
b1000 J
b11111110001 O
#132500
1%
1E
b0 L
b11111110001 P
1I
#133000
0%
0E
b10000010 4
1$
b10 !
0>
1D
b1 K
b0 J
b0 O
#133500
1%
1E
b1 L
b11 N
0I
1H
b11111110001 G
13
00
0/
1.
1,
#134000
0%
0E
b101 6
b101 '
b10000011 4
0$
1#
b10 "
b1000 !
0=
1;
0B
0D
1C
b11 K
#134500
1%
1E
b11 L
b1000 M
0H
03
b10 K
#135000
0%
0E
b10000100 4
b1111 "
b1 !
1>
0;
1B
1@
1?
b1 J
b11111101000 O
#135500
1%
1E
b10 L
b1 M
b11111101000 P
#136000
0%
0E
b10000101 4
0#
b110 "
b1110 !
0>
1=
1<
1;
0B
0?
0C
#136500
1%
1E
#137000
0%
0E
b10000110 4
1$
b111 "
b110 !
0;
1B
1D
b11 K
#137500
1%
1E
b11 L
b111 N
b1 K
#138000
0%
0E
b10000111 4
0$
b1111 !
1>
1;
0D
b0 K
b10 J
b11111101111 O
#138500
1%
1E
b0 L
b11111101111 P
#139000
0%
0E
b10001000 4
b1 "
b1101 !
0=
0A
0@
#139500
1%
1E
#140000
0%
0E
b10001001 4
b11 !
1=
0<
0;
#140500
1%
1E
#141000
0%
0E
b10001010 4
1$
b1111 "
b111 !
1<
1A
1@
1?
1D
b1 K
#141500
1%
1E
b1 L
b1111 N
#142000
0%
0E
b10001011 4
0$
1#
b0 "
b1111 !
1;
0B
0A
0@
0?
0D
1C
b11 K
#142500
1%
1E
b11 L
b1111 M
b10 K
#143000
0%
0E
b10001100 4
0#
b101 "
b1001 !
0=
0<
1B
1@
0C
b0 K
b11 J
b11111110000 O
#143500
1%
1E
b0 L
b11111110000 P
#144000
0%
0E
b10001101 4
b0 !
0>
0;
#144500
1%
1E
#145000
0%
0E
b10001110 4
1$
b111 "
b1010 !
1=
1;
1A
1D
b1 K
#145500
1%
1E
b1 L
b111 N
#146000
0%
0E
b10001111 4
0$
b101 "
b1001 !
1>
0=
0A
0D
#146500
1%
1E
#147000
0%
0E
b10010000 4
b10 "
b110 !
0>
1=
1<
0;
0B
1A
0@
#147500
1%
1E
#148000
0%
0E
b10010001 4
1#
b1100 !
0=
1;
1C
b11 K
#148500
1%
1E
b11 L
b1100 M
b10 K
#149000
0%
0E
b10010010 4
1$
1D
b11 K
b100 J
b11111010100 O
#149500
1%
1E
b10 N
b11111010100 P
#150000
0%
0E
b10010011 4
b0 !
0<
0;
b101 J
b11111001100 O
#150500
1%
1E
b0 M
b11111001100 P
#151000
0%
0E
b10010100 4
b0 "
b1001 !
1>
1;
0A
b110 J
#151500
1%
1E
b1001 M
b0 N
#152000
0%
0E
b10010101 4
0$
0#
b110 "
b1 !
0;
1A
1@
0D
0C
b0 K
b111 J
#152500
1%
1E
b0 L
#153000
0%
0E
b10010110 4
b1110 !
0>
1=
1<
1;
#153500
1%
1E
#154000
0%
0E
b10010111 4
b10 "
b1101 !
1>
0=
0@
#154500
1%
1E
#155000
0%
0E
b10011000 4
1$
b1111 "
b1100 !
0>
1B
1@
1?
1D
b1 K
#155500
1%
1E
b1 L
b1111 N
#156000
0%
0E
b10011001 4
0$
1#
b11 "
b1101 !
1>
0@
0?
0D
1C
b11 K
#156500
1%
1E
b11 L
b1101 M
b10 K
#157000
0%
0E
b10011010 4
b111 "
1@
b1000 J
b11111001111 O
#157500
1%
1E
b10 L
b11111001111 P
1I
#158000
0%
0E
b10011011 4
0#
b1111 "
b111 !
1=
0;
1?
0C
b0 J
b0 O
#158500
1%
1E
0I
1H
b11111001111 G
13
11
10
1/
0.
0-
#159000
0%
0E
b110 6
b110 '
b10011100 4
1$
b110 "
b1000 !
0>
0=
0<
1;
0B
0?
1D
b11 K
#159500
1%
1E
b11 L
b110 N
0H
03
b1 K
#160000
0%
0E
b10011101 4
1#
b1111 !
1>
1=
1<
1C
b11 K
b1 J
b11111101110 O
#160500
1%
1E
b1111 M
b11111101110 P
#161000
0%
0E
b10011110 4
0#
b1001 !
0=
0<
0C
b1 K
b10 J
b11111101000 O
#161500
1%
1E
b1 L
b11111101000 P
#162000
0%
0E
b10011111 4
0$
1#
b10 !
0>
1=
0;
0D
1C
b11 K
#162500
1%
1E
b11 L
b10 M
b10 K
#163000
0%
0E
b10100000 4
b10 "
b1010 !
1;
0@
b11 J
b11111110100 O
#163500
1%
1E
b10 L
b1010 M
b11111110100 P
#164000
0%
0E
b10100001 4
1$
0#
b100 "
b1011 !
1>
0A
1@
1D
0C
b11 K
#164500
1%
1E
b11 L
b100 N
b1 K
